giftool2/__init__.py
giftool2/app.py
giftool2/main.py
giftool2/static/app.js
giftool2/static/download-solid.svg
giftool2/static/style.css
giftool2/static/trash-solid.svg
giftool2/templates/gif_list.html
giftool2/templates/index.html
giftool2-0.22.0.dist-info/METADATA
giftool2-0.22.0.dist-info/WHEEL
giftool2-0.22.0.dist-info/entry_points.txt
giftool2-0.22.0.dist-info/RECORD
