Metadata-Version: 2.4
Name: giftool2
Version: 0.22.0
Summary: a simple tool to extract video to gif
Project-URL: Homepage, https://github.com/michaeldini/giftool2
Project-URL: Repository, https://github.com/michaeldini/giftool2
Author: Michael Dini
License-Expression: MIT AND (Apache-2.0 OR BSD-2-Clause)
Keywords: gif,video
Classifier: Development Status :: 3 - Alpha
Classifier: Framework :: Flask
Classifier: Framework :: Hatch
Classifier: Intended Audience :: Developers
Classifier: Intended Audience :: End Users/Desktop
Classifier: Programming Language :: Python :: 3
Classifier: Topic :: Multimedia :: Graphics :: Editors
Requires-Python: >=3.9
Requires-Dist: ffmpeg-python>=0.2.0
Requires-Dist: flask
Requires-Dist: opencv-python
Requires-Dist: pillow>=11.2.1
Requires-Dist: pytest>=8.3.5
